minitorch_framework/__init__.py
minitorch_framework/examples/__init__.py
minitorch_framework/examples/test_10x12_system.py
minitorch_framework/examples/train_complete_model.py
minitorch_framework/examples/train_full_model.py
minitorch_framework/models/__init__.py
minitorch_framework/models/transformer_rlm.py
minitorch_framework/rl/__init__.py
minitorch_framework/rl/reinforcement_learning.py
minitorch_framework/vllm/__init__.py
minitorch_framework/vllm/relational_vllm.py
tenminator-0.1.0.dist-info/METADATA
tenminator-0.1.0.dist-info/WHEEL
tenminator-0.1.0.dist-info/entry_points.txt
tenminator-0.1.0.dist-info/top_level.txt
tenminator-0.1.0.dist-info/RECORD
