Metadata-Version: 2.1
Name: tenminator
Version: 0.1.0
Summary: Framework de Deep Learning ultraligero inspirado en PyTorch para dispositivos con almacenamiento limitado
Home-page: https://github.com/tu-usuario/tenminator
Author: TenMiNaTor Team
Author-email: support@tenminator.dev
Project-URL: Bug Reports, https://github.com/tu-usuario/tenminator/issues
Project-URL: Documentation, https://tenminator.dev/docs
Project-URL: Source, https://github.com/tu-usuario/tenminator
Keywords: deep-learning machine-learning pytorch tensorflow neural-networks autograd lightweight
Classifier: Development Status :: 4 - Beta
Classifier: Intended Audience :: Developers
Classifier: Intended Audience :: Science/Research
Classifier: License :: OSI Approved :: MIT License
Classifier: Programming Language :: Python :: 3
Classifier: Programming Language :: Python :: 3.8
Classifier: Programming Language :: Python :: 3.9
Classifier: Programming Language :: Python :: 3.10
Classifier: Programming Language :: Python :: 3.11
Classifier: Topic :: Scientific/Engineering :: Artificial Intelligence
Classifier: Topic :: Software Development :: Libraries :: Python Modules
Requires-Python: >=3.8
Requires-Dist: numpy>=1.21.0
Provides-Extra: all
Requires-Dist: jax>=0.4.0; extra == "all"
Requires-Dist: jaxlib>=0.4.0; extra == "all"
Requires-Dist: cupy>=11.0.0; extra == "all"
Requires-Dist: numba>=0.56.0; extra == "all"
Requires-Dist: sqlalchemy>=2.0.0; extra == "all"
Requires-Dist: pymongo>=4.0.0; extra == "all"
Requires-Dist: firebase-admin>=6.0.0; extra == "all"
Requires-Dist: beautifulsoup4>=4.11.0; extra == "all"
Requires-Dist: requests>=2.28.0; extra == "all"
Requires-Dist: networkx>=3.0; extra == "all"
Requires-Dist: pydantic>=2.0.0; extra == "all"
Requires-Dist: pandas>=2.0.0; extra == "all"
Provides-Extra: cupy
Requires-Dist: cupy>=11.0.0; extra == "cupy"
Provides-Extra: database
Requires-Dist: sqlalchemy>=2.0.0; extra == "database"
Requires-Dist: pymongo>=4.0.0; extra == "database"
Requires-Dist: firebase-admin>=6.0.0; extra == "database"
Provides-Extra: dataframe
Requires-Dist: pandas>=2.0.0; extra == "dataframe"
Provides-Extra: graph
Requires-Dist: networkx>=3.0; extra == "graph"
Provides-Extra: jax
Requires-Dist: jax>=0.4.0; extra == "jax"
Requires-Dist: jaxlib>=0.4.0; extra == "jax"
Provides-Extra: numba
Requires-Dist: numba>=0.56.0; extra == "numba"
Provides-Extra: validation
Requires-Dist: pydantic>=2.0.0; extra == "validation"
Provides-Extra: web
Requires-Dist: beautifulsoup4>=4.11.0; extra == "web"
Requires-Dist: requests>=2.28.0; extra == "web"
